{"chunk_definitions":[{"row":34,"row_count":1,"visible":true,"expansion_state":0,"options":{"echo":false,"engine":"r","label":"unnamed-chunk-50"},"document_id":"4C62A528","chunk_id":"czkxwurvlb18q","chunk_label":"unnamed-chunk-1"},{"row":64,"row_count":1,"visible":true,"expansion_state":0,"options":{"warning":false,"message":false,"engine":"r","label":"unnamed-chunk-51"},"document_id":"4C62A528","chunk_id":"c36nk6dmgav58","chunk_label":"unnamed-chunk-2"},{"row":93,"row_count":1,"visible":true,"expansion_state":0,"options":{"engine":"r","label":"unnamed-chunk-52"},"document_id":"4C62A528","chunk_id":"c4eeumulr0wpf","chunk_label":"unnamed-chunk-3"},{"row":111,"row_count":1,"visible":true,"expansion_state":0,"options":{"engine":"r","label":"unnamed-chunk-53"},"document_id":"4C62A528","chunk_id":"cpbjpvgyzj5ss","chunk_label":"unnamed-chunk-4"},{"row":123,"row_count":1,"visible":true,"expansion_state":0,"options":{"engine":"r","label":"unnamed-chunk-54"},"document_id":"4C62A528","chunk_id":"cnstawr8yii83","chunk_label":"unnamed-chunk-5"},{"row":137,"row_count":1,"visible":true,"expansion_state":0,"options":{"warning":false,"engine":"r","label":"unnamed-chunk-55"},"document_id":"4C62A528","chunk_id":"cxpomlcyzd137","chunk_label":"unnamed-chunk-6"},{"row":217,"row_count":1,"visible":true,"expansion_state":0,"options":{"engine":"r","label":"unnamed-chunk-56"},"document_id":"4C62A528","chunk_id":"clbvmlutn3g46","chunk_label":"unnamed-chunk-7"},{"row":229,"row_count":1,"visible":true,"expansion_state":0,"options":{"engine":"r","label":"unnamed-chunk-57"},"document_id":"4C62A528","chunk_id":"c8q2kp9wgwzdp","chunk_label":"unnamed-chunk-8"},{"row":240,"row_count":1,"visible":true,"expansion_state":0,"options":{"engine":"r","label":"unnamed-chunk-58"},"document_id":"4C62A528","chunk_id":"cfivp4uzt8xc9","chunk_label":"unnamed-chunk-9"},{"row":252,"row_count":1,"visible":true,"expansion_state":0,"options":{"engine":"r","label":"unnamed-chunk-59"},"document_id":"4C62A528","chunk_id":"cffld2knjehmg","chunk_label":"unnamed-chunk-10"},{"row":270,"row_count":1,"visible":true,"expansion_state":0,"options":{"engine":"r","label":"unnamed-chunk-60"},"document_id":"4C62A528","chunk_id":"c8rp7q7b5s0k7","chunk_label":"unnamed-chunk-11"},{"row":299,"row_count":1,"visible":true,"expansion_state":0,"options":{"code-fold":true,"engine":"r","label":"unnamed-chunk-61"},"document_id":"4C62A528","chunk_id":"c6df18yozz5jl","chunk_label":"unnamed-chunk-12"},{"row":330,"row_count":1,"visible":true,"expansion_state":0,"options":{"code-fold":true,"engine":"r","label":"unnamed-chunk-62"},"document_id":"4C62A528","chunk_id":"ck1mk1kg2iolw","chunk_label":"unnamed-chunk-13"},{"row":355,"row_count":1,"visible":true,"expansion_state":0,"options":{"message":false,"warning":false,"code-fold":true,"engine":"r","label":"unnamed-chunk-63"},"document_id":"4C62A528","chunk_id":"cab20g1kdt9q1","chunk_label":"unnamed-chunk-14"},{"row":484,"row_count":1,"visible":true,"expansion_state":0,"options":{"code-fold":true,"engine":"r","label":"unnamed-chunk-64"},"document_id":"4C62A528","chunk_id":"cuga6ey0z9apm","chunk_label":"unnamed-chunk-15"},{"row":497,"row_count":1,"visible":true,"expansion_state":0,"options":{"code-fold":true,"engine":"r","label":"unnamed-chunk-65"},"document_id":"4C62A528","chunk_id":"c6k442kiryrl3","chunk_label":"unnamed-chunk-16"},{"row":511,"row_count":1,"visible":true,"expansion_state":0,"options":{"code-fold":true,"engine":"r","label":"unnamed-chunk-66"},"document_id":"4C62A528","chunk_id":"c9ipvxd8rq3d6","chunk_label":"unnamed-chunk-17"},{"row":521,"row_count":1,"visible":true,"expansion_state":0,"options":{"code-fold":true,"engine":"r","label":"unnamed-chunk-67"},"document_id":"4C62A528","chunk_id":"c3bh7llfe67jq","chunk_label":"unnamed-chunk-18"},{"row":572,"row_count":1,"visible":true,"expansion_state":0,"options":{"code-fold":true,"engine":"r","label":"unnamed-chunk-123"},"document_id":"4C62A528","chunk_id":"ci1s3mt7ci3jb","chunk_label":"unnamed-chunk-19"},{"row":598,"row_count":1,"visible":true,"expansion_state":0,"options":{"code-fold":true,"engine":"r","label":"unnamed-chunk-24"},"document_id":"4C62A528","chunk_id":"cg1sak6xdg76k","chunk_label":"unnamed-chunk-20"},{"row":619,"row_count":1,"visible":true,"expansion_state":0,"options":{"code-fold":true,"engine":"r","label":"unnamed-chunk-25"},"document_id":"4C62A528","chunk_id":"clsf2g75qczde","chunk_label":"unnamed-chunk-21"},{"row":640,"row_count":1,"visible":true,"expansion_state":0,"options":{"code-fold":true,"engine":"r","label":"unnamed-chunk-26"},"document_id":"4C62A528","chunk_id":"cydx4jml0ppqb","chunk_label":"unnamed-chunk-22"},{"row":656,"row_count":1,"visible":true,"expansion_state":0,"options":{"code-fold":true,"engine":"r","label":"unnamed-chunk-37"},"document_id":"4C62A528","chunk_id":"cjmni4iay8acu","chunk_label":"unnamed-chunk-23"},{"row":670,"row_count":1,"visible":true,"expansion_state":0,"options":{"code-fold":true,"engine":"r","label":"unnamed-chunk-38"},"document_id":"4C62A528","chunk_id":"coizcg7s44rlg","chunk_label":"unnamed-chunk-24"},{"row":701,"row_count":1,"visible":true,"expansion_state":0,"options":{"code-fold":true,"engine":"r","label":"unnamed-chunk-89"},"document_id":"4C62A528","chunk_id":"cys97zmsi37rt","chunk_label":"unnamed-chunk-25"},{"row":735,"row_count":1,"visible":true,"expansion_state":0,"options":{"code-fold":true,"engine":"r","label":"unnamed-chunk-101"},"document_id":"4C62A528","chunk_id":"cywdrry201nzb","chunk_label":"unnamed-chunk-26"},{"row":760,"row_count":1,"visible":true,"expansion_state":0,"options":{"code-fold":true,"fig.align":"center","engine":"r","label":"unnamed-chunk-130"},"document_id":"4C62A528","chunk_id":"cpfyed30as1uc","chunk_label":"unnamed-chunk-27"}],"doc_write_time":1704288492,"chunk_rendered_width":643}